odoo/addons/ssi_psychology_consultation/README.rst
odoo/addons/ssi_psychology_consultation/__init__.py
odoo/addons/ssi_psychology_consultation/__manifest__.py
odoo/addons/ssi_psychology_consultation/data/approval_template_data.xml
odoo/addons/ssi_psychology_consultation/data/ir_sequence_data.xml
odoo/addons/ssi_psychology_consultation/data/policy_template_data.xml
odoo/addons/ssi_psychology_consultation/data/sequence_template_data.xml
odoo/addons/ssi_psychology_consultation/demo/psychology_consultation_type_demo.xml
odoo/addons/ssi_psychology_consultation/models/__init__.py
odoo/addons/ssi_psychology_consultation/models/psychology_consultation.py
odoo/addons/ssi_psychology_consultation/models/psychology_consultation_type.py
odoo/addons/ssi_psychology_consultation/security/ir.model.access.csv
odoo/addons/ssi_psychology_consultation/security/ir_module_category_data.xml
odoo/addons/ssi_psychology_consultation/security/ir_rule_data.xml
odoo/addons/ssi_psychology_consultation/security/res_group_data.xml
odoo/addons/ssi_psychology_consultation/static/description/icon.png
odoo/addons/ssi_psychology_consultation/views/psychology_consultation_type_views.xml
odoo/addons/ssi_psychology_consultation/views/psychology_consultation_views.xml
odoo14_addon_ssi_psychology_consultation-14.0.1.5.0.dist-info/METADATA
odoo14_addon_ssi_psychology_consultation-14.0.1.5.0.dist-info/WHEEL
odoo14_addon_ssi_psychology_consultation-14.0.1.5.0.dist-info/top_level.txt
odoo14_addon_ssi_psychology_consultation-14.0.1.5.0.dist-info/RECORD
